ExitNotifier/__init__.py
ExitNotifier/exit_notifier.py
exit_notifier-0.0.1.dist-info/LICENSE
exit_notifier-0.0.1.dist-info/METADATA
exit_notifier-0.0.1.dist-info/WHEEL
exit_notifier-0.0.1.dist-info/entry_points.txt
exit_notifier-0.0.1.dist-info/RECORD
